[
	{
		"number":"A0001",
		"name":"환경 친화적인 비닐개발",
		"endDate":"2019-07-05 17:00:30",
		"total":1000000,
		"current":5000
	},
	{
		"number":"A0002",
		"name":"돈안내고 스팀 게임하기",
		"endDate":"2019-06-15 17:00:30",
		"total":50000,
		"current":20000
	},
	{
		"number":"A0003",
		"name":"마감된 펀드",
		"endDate":"2019-05-01 15:30:00",
		"total":40000,
		"current":35000
	},
	{
		"number":"A0004",
		"name":"자바 공부 교재 개발하기",
		"endDate":"2019-12-31 08:30:00",
		"total":2000000,
		"current":0
	},
	{
		"number":"A0005",
		"name":"기능반 간식비 프로젝트",
		"endDate":"2019-07-11 09:00:00",
		"total":1000000,
		"current":500
	},
	{
		"number":"A0006",
		"name":"이석 살찌우기",
		"endDate":"2020-11-14 23:16:33",
		"total":16000,
		"current":1300
	},
	{
		"number":"A0007",
		"name":"고헌준 살빼기",
		"endDate":"2021-05-03 17:00:00",
		"total":750000,
		"current":160000
	},
	{
		"number":"A0008",
		"name":"정효민 허리펴기",
		"endDate":"2020-11-27 12:12:00",
		"total":2000000,
		"current":470000
	},
	{
		"number":"A0009",
		"name":"김민규 식비 할당하기",
		"endDate":"2020-12-31 16:44:30",
		"total":500,
		"current":470
	},
	{
		"number":"A0010",
		"name":"박현진 사람만들기",
		"endDate":"2022-11-30 12:00:00",
		"total":10000000,
		"current":150000
	},
	{
		"number":"A0011",
		"name":"<script>alert('&nbsp;');</script>",
		"endDate":"2020-11-26 12:55:00",
		"total":500000,
		"current":350000
	},
	{
		"number":"A0012",
		"name":"박인환 기능반 내쫓기",
		"endDate":"2021-07-10 23:59:59",
		"total":100,
		"current":30
	},
	{
		"number":"A0013",
		"name":"박지성 일본 보내기121223134243232442342332",
		"endDate":"2020-11-14 23:59:59",
		"total":5000000,
		"current":3890000
	},
	{
		"number":"A0014",
		"name":"박명재 고소하기",
		"endDate":"2025-01-01 00:00:00",
		"total":1268000,
		"current":600000
	}
]